[{"name":"wikindexer","path":"dist/wikindexer_linux_arm64/wikindexer","goos":"linux","goarch":"arm64","internal_type":4,"type":"Binary","extra":{"Binary":"wikindexer","Ext":"","ID":"wikindexer"}},{"name":"wikindexer","path":"dist/wikindexer_linux_amd64_v1/wikindexer","goos":"linux","goarch":"amd64","goamd64":"v1","internal_type":4,"type":"Binary","extra":{"Binary":"wikindexer","Ext":"","ID":"wikindexer"}},{"name":"wikindexer","path":"dist/wikindexer_darwin_amd64_v1/wikindexer","goos":"darwin","goarch":"amd64","goamd64":"v1","internal_type":4,"type":"Binary","extra":{"Binary":"wikindexer","Ext":"","ID":"wikindexer"}},{"name":"wikindexer","path":"dist/wikindexer_darwin_arm64/wikindexer","goos":"darwin","goarch":"arm64","internal_type":4,"type":"Binary","extra":{"Binary":"wikindexer","Ext":"","ID":"wikindexer"}}]